CHANGELOG.md
LICENSE.txt
MANIFEST.in
README.md
setup.py
factual/__init__.py
factual/api.py
factual/query/__init__.py
factual/query/base.py
factual/query/boost.py
factual/query/clear.py
factual/query/diffs.py
factual/query/facets.py
factual/query/flag.py
factual/query/geocode.py
factual/query/insert.py
factual/query/match.py
factual/query/multi.py
factual/query/read.py
factual/query/resolve.py
factual/query/submit.py
factual/query/table.py
factual/query/write.py
factual/utils/__init__.py
factual/utils/utils.py
factual_api.egg-info/PKG-INFO
factual_api.egg-info/SOURCES.txt
factual_api.egg-info/dependency_links.txt
factual_api.egg-info/requires.txt
factual_api.egg-info/top_level.txt
tests/__init__.py
tests/api_test.py
tests/test_settings.py.template