Metadata-Version: 1.1
Name: factual-api
Version: 1.6.0
Summary: Official Python driver for the Factual public API
Home-page: http://github.com/Factual/factual-python-driver
Author: Factual Driver Team
Author-email: UNKNOWN
License: Apache License
Keywords: factual
Platform: UNKNOWN
Classifier: Development Status :: 5 - Production/Stable
Classifier: Intended Audience :: Developers
Classifier: License :: OSI Approved :: Apache Software License
Classifier: Programming Language :: Python
Classifier: Operating System :: OS Independent
Classifier: Topic :: Internet :: WWW/HTTP
Classifier: Topic :: Software Development :: Libraries :: Python Modules
